pysvt/__init__.py
pysvt/__main__.py
pysvt/utils/__init__.py
pysvt/utils/ctx.py
pysvt/utils/models.py
pysvt/utils/printer.py
pysvt/utils/validation.py
pysvt-0.6.0.dist-info/LICENSE
pysvt-0.6.0.dist-info/METADATA
pysvt-0.6.0.dist-info/WHEEL
pysvt-0.6.0.dist-info/RECORD
