Metadata-Version: 2.1
Name: pysvt
Version: 0.6.0
Summary: A simple test case runner in Python that uses TOML configurations and decorator syntax.
License: LICENSE
Author: dhzdhd
Author-email: dhzdhd@proton.me
Requires-Python: >=3.8.1,<4.0.0
Classifier: License :: OSI Approved :: MIT License
Classifier: License :: Other/Proprietary License
Classifier: Operating System :: OS Independent
Classifier: Programming Language :: Python :: 3
Classifier: Programming Language :: Python :: 3.9
Classifier: Programming Language :: Python :: 3.10
Classifier: Programming Language :: Python :: 3.11
Classifier: Programming Language :: Python :: 3.12
Classifier: Programming Language :: Python :: 3.8
Requires-Dist: rich (>=13.7.0,<14.0.0)
